{"uniqueName":"/Lotus/Types/Sentinels/SentinelPowersuits/ShadePowerSuit","name":"Shade","health":600,"shield":130,"armor":80,"stamina":8,"power":100,"description":"With 'Revenge' and 'Ghost' as default Precepts, Shade is well suited for stealth gameplay. Shade also comes with a burst laser pistol.","productCategory":"Sentinels","buildQuantity":1,"type":"Sentinel","imageName":"Shade.png","category":"Sentinels","tradable":false,"wikiAvailable":true,"masteryReq":0,"polarities":["penjaga","penjaga","penjaga","penjaga"],"isPrime":false,"masterable":true}