{"name":"Balefire Charger","uniqueName":"/Lotus/Powersuits/IronFrame/BlastWeapon","damagePerShot":[0,0,0,0,0,0,0,0,0,0,0,0,0,0,0,0,0,0,0,0],"totalDamage":0,"description":"Charges up and releases bolts of Balefire.","criticalChance":0.050000001,"criticalMultiplier":1.5,"procChance":0.10000002,"fireRate":0.83333337,"masteryReq":0,"productCategory":"SpecialItems","excludeFromCodex":true,"slot":7,"accuracy":100,"omegaAttenuation":1,"noise":"Alarming","trigger":"Charge","reloadTime":1,"multishot":1,"type":"Exalted Weapon","imageName":"balefire-charger-b6c85f25c8.png","category":"Misc","tradable":false,"patchlogs":[{"name":"Update 31.1.0: Echoes of War","date":"2022-02-09T15:59:43Z","url":"https://forums.warframe.com/topic/1299619-update-3110-echoes-of-war/","additions":"","changes":"Hildryn arises anew, re-forged in the fires of finest smith-craft. Add splendor to her saga with this collection of deluxe items.The Einheri skin includes a new look for Hildryn’s Balefire Charger. The Deluxe Bundle includes the Hildryn Einheri Skin, Blodgard Heavy Blade Skin and the Brising Syandana.","fixes":""},{"name":"Warframe Revised: Railjack Revisited (Part 1): Update 27.4","date":"2020-05-01T13:21:46Z","url":"https://forums.warframe.com/topic/1189247-warframe-revised-railjack-revisited-part-1-update-274/","additions":"","changes":"","fixes":"Fixed both Charged Damage and Quick Shot Damage of Hildryn’s Balefire Charger Damage displaying the same value in the Arsenal."}],"wikiAvailable":true,"attacks":[{"name":"Uncharged Shot","speed":0.833,"crit_chance":5,"crit_mult":1.5,"status_chance":10,"shot_type":"AoE","shot_speed":80,"flight":80,"falloff":{"start":0,"end":3,"reduction":0},"damage":{"electricity":500}},{"name":"Charged Shot","speed":0.833,"crit_chance":5,"crit_mult":1.5,"status_chance":10,"charge_time":2,"shot_type":"AoE","shot_speed":80,"flight":80,"falloff":{"start":0,"end":3,"reduction":0},"damage":{"electricity":1500}},{"name":"Alt Fire Shot","speed":0.75,"crit_chance":5,"crit_mult":1.5,"status_chance":10,"shot_type":"AoE","shot_speed":80,"flight":80,"falloff":{"start":0,"end":3,"reduction":0},"damage":{"electricity":500}}],"polarities":["madurai","madurai"],"tags":["Tenno"],"wikiaThumbnail":"https://wiki.warframe.com/images/BalefireCharger.png?6752e","wikiaUrl":"https://wiki.warframe.com/w/Balefire_Charger","introduced":{"name":"Update 24.4","url":"https://wiki.warframe.com/w/Update_24%23Update_24.4","aliases":["24.4","24.4.0"],"parent":"24.4","date":"2019-03-08"},"disposition":3,"releaseDate":"2019-03-08","masterable":false}